README
setup.py
scrape_quora/__init__.py
scrape_quora/pyquora.py
scrape_quora/test.py
scrape_quora.egg-info/PKG-INFO
scrape_quora.egg-info/SOURCES.txt
scrape_quora.egg-info/dependency_links.txt
scrape_quora.egg-info/top_level.txt