Metadata-Version: 1.0
Name: scrape-quora
Version: 0.1.3
Summary: Fetches and parses data from Quora user profiles
Home-page: https://github.com/hansika/pyquora
Author: Hansika Hewamalage
Author-email: pehesarani@gmail.com
License: UNKNOWN
Platform: UNKNOWN
